api_sdk_python-0.1.0.dist-info/DESCRIPTION.rst
api_sdk_python-0.1.0.dist-info/METADATA
api_sdk_python-0.1.0.dist-info/RECORD
api_sdk_python-0.1.0.dist-info/WHEEL
api_sdk_python-0.1.0.dist-info/metadata.json
api_sdk_python-0.1.0.dist-info/top_level.txt
banregioapi/__init__.py
banregioapi/banregio_api_helper.py
banregioapi/banregio_token_helper.py
banregioapi/resources/__init__.py
banregioapi/resources/account.py
banregioapi/resources/transaction.py
banregioapi/utils/__init__.py
banregioapi/utils/service.py
